skipper_tool/.DS_Store
skipper_tool/__init__.py
skipper_tool/annotate.py
skipper_tool/boxes.py
skipper_tool/config.py
skipper_tool/inference_logger.py
skipper_tool/keystrokes.py
skipper_tool/omniparser/__init__.py
skipper_tool/omniparser/annotation.py
skipper_tool/omniparser/client.py
skipper_tool/omniparser/engine.py
skipper_tool/omniparser/local.py
skipper_tool/omniparser/ocr.py
skipper_tool/omniparser/remote.py
skipper_tool/profiling.py
skipper_tool/reduce.py
skipper_tool/scripts/__init__.py
skipper_tool/scripts/analyze_inference_logs.py
skipper_tool/scripts/annotate_screenshot.py
skipper_tool/scripts/main.py
skipper_tool/test_boxes.py
skipper_tool-0.2.13.dist-info/WHEEL
skipper_tool-0.2.13.dist-info/entry_points.txt
skipper_tool-0.2.13.dist-info/METADATA
skipper_tool-0.2.13.dist-info/RECORD
