Metadata-Version: 2.3
Name: skipper-tool
Version: 0.2.13
Summary: A desktop interaction tool that allows AI agents like Claude Code or OpenAI Codex to control web browsers and interact with desktop applications through natural language commands.
Requires-Dist: numpy
Requires-Dist: playwright
Requires-Dist: openai
Requires-Dist: ruff
Requires-Dist: beautifulsoup4
Requires-Dist: pillow
Requires-Dist: loguru
Requires-Dist: rich
Requires-Dist: pytest
Requires-Dist: tomli
Requires-Dist: requests
Requires-Dist: setuptools
Requires-Dist: torch ; extra == 'local'
Requires-Dist: torchvision ; extra == 'local'
Requires-Dist: supervision ; extra == 'local'
Requires-Dist: ultralytics ; extra == 'local'
Requires-Dist: transformers ; extra == 'local'
Requires-Dist: opencv-python-headless ; extra == 'local'
Requires-Dist: paddleocr==3.2.0 ; extra == 'omniparser'
Requires-Dist: paddlepaddle-gpu ; extra == 'omniparser'
Requires-Python: >=3.10
Project-URL: Homepage, https://github.com/moonshinelabs-ai/skipper-tool
Project-URL: Issues, https://github.com/moonshinelabs-ai/skipper-tool/issues
Provides-Extra: local
Provides-Extra: omniparser
